multiplexor/__init__.py
multiplexor/__main__.py
multiplexor/_version.py
multiplexor/examples/__init__.py
multiplexor/examples/mpsocks5.py
multiplexor/logger/__init__.py
multiplexor/logger/logger.py
multiplexor/logger/objects.py
multiplexor/operator/__init__.py
multiplexor/operator/exceptions.py
multiplexor/operator/operator.py
multiplexor/operator/protocol.py
multiplexor/operator/external/__init__.py
multiplexor/operator/external/sspi.py
multiplexor/operator/local/__init__.py
multiplexor/operator/local/socks5.py
multiplexor/operator/local/sspi.py
multiplexor/operator/local/common/__init__.py
multiplexor/operator/local/common/connector.py
multiplexor/operator/local/common/listener.py
multiplexor/plugins/__init__.py
multiplexor/plugins/plugins.py
multiplexor/plugins/plugintypes.py
multiplexor/plugins/remoting/__init__.py
multiplexor/plugins/remoting/plugin.py
multiplexor/plugins/socks5/__init__.py
multiplexor/plugins/socks5/plugin.py
multiplexor/plugins/socks5/plugininfo.py
multiplexor/plugins/socks5/pluginprotocol.py
multiplexor/plugins/socks5/pluginsettings.py
multiplexor/plugins/socks5/socks5protocol.py
multiplexor/plugins/sspi/__init__.py
multiplexor/plugins/sspi/plugin.py
multiplexor/plugins/sspi/plugininfo.py
multiplexor/plugins/sspi/pluginprotocol.py
multiplexor/plugins/sspi/pluginsettings.py
multiplexor/server/__init__.py
multiplexor/server/server.py
multiplexor/server/agent/__init__.py
multiplexor/server/agent/agent.py
multiplexor/server/operator/__init__.py
multiplexor/server/operator/operatorhandler.py
multiplexor/server/packetizer/__init__.py
multiplexor/server/packetizer/packetizer.py
multiplexor/server/protocol/__init__.py
multiplexor/server/protocol/protocol.py
multiplexor/server/transports/__init__.py
multiplexor/server/transports/http11.py
multiplexor/server/transports/websockets.py
multiplexor/utils/__init__.py
multiplexor/utils/apq.py
multiplexor-0.0.13.dist-info/METADATA
multiplexor-0.0.13.dist-info/WHEEL
multiplexor-0.0.13.dist-info/entry_points.txt
multiplexor-0.0.13.dist-info/top_level.txt
multiplexor-0.0.13.dist-info/zip-safe
multiplexor-0.0.13.dist-info/RECORD
