Metadata-Version: 2.1
Name: multiplexor
Version: 0.0.13
Summary: multiplexor
Home-page: https://github.com/skelsec/multiplexor
Author: Tamas Jos
Author-email: info@skelsec.com
License: UNKNOWN
Platform: UNKNOWN
Classifier: Programming Language :: Python :: 3.7
Classifier: Operating System :: OS Independent
Requires-Python: >=3.7
Requires-Dist: websockets
